quotation/__init__.py
quotation/constants.py
quotation/errors.py
quotation/models.py
quotation/ngram.py
quotation/query.py
quotation/sanitize.py
quotation/utiles.py
quotation/indexr/__init__.py
quotation/indexr/build.py
quotation/indexr/models.py
arabic_text_quote-0.0.2.dist-info/LICENSE
arabic_text_quote-0.0.2.dist-info/METADATA
arabic_text_quote-0.0.2.dist-info/WHEEL
arabic_text_quote-0.0.2.dist-info/top_level.txt
arabic_text_quote-0.0.2.dist-info/RECORD
