Metadata-Version: 2.1
Name: arabic-text-quote
Version: 0.0.2
Summary: A package to discover texts extracted from Arabic books
Home-page: https://github.com/abdullh-alidrous/arabic-text-quotation
Author: Abdullah Al-Aidrous
Author-email: abdullah.alidrous@gmail.com
License: UNKNOWN
Platform: UNKNOWN
Classifier: Programming Language :: Python :: 3
Classifier: License :: OSI Approved :: MIT License
Classifier: Operating System :: OS Independent
Requires-Python: >=3.6
